{
  "name": "Rondônia",
  "cities": [
    {
      "name": "Alta Floresta d'Oeste",
      "official_gazette_url": null
    },
    {
      "name": "Alto Alegre do Parecis",
      "official_gazette_url": null
    },
    {
      "name": "Alto Paraíso",
      "official_gazette_url": null
    },
    {
      "name": "Alvorada d'Oeste",
      "official_gazette_url": null
    },
    {
      "name": "Ariquemes",
      "official_gazette_url": null
    },
    {
      "name": "Buritis",
      "official_gazette_url": "https://www.buritis.ro.gov.br/"
    },
    {
      "name": "Cabixi",
      "official_gazette_url": null
    },
    {
      "name": "Cacaulândia",
      "official_gazette_url": null
    },
    {
      "name": "Cacoal",
      "official_gazette_url": null
    },
    {
      "name": "Campo Novo de Rondônia",
      "official_gazette_url": null
    },
    {
      "name": "Candeias do Jamari",
      "official_gazette_url": null
    },
    {
      "name": "Castanheiras",
      "official_gazette_url": "https://www.diariomunicipal.com.br/arom/"
    },
    {
      "name": "Cerejeiras",
      "official_gazette_url": null
    },
    {
      "name": "Chupinguaia",
      "official_gazette_url": null
    },
    {
      "name": "Colorado do Oeste",
      "official_gazette_url": null
    },
    {
      "name": "Corumbiara",
      "official_gazette_url": "https://corumbiara.ro.gov.br/legislacao/"
    },
    {
      "name": "Costa Marques",
      "official_gazette_url": null
    },
    {
      "name": "Cujubim",
      "official_gazette_url": null
    },
    {
      "name": "Espigão d'Oeste",
      "official_gazette_url": null
    },
    {
      "name": "Governador Jorge Teixeira",
      "official_gazette_url": null
    },
    {
      "name": "Guajará-Mirim",
      "official_gazette_url": null
    },
    {
      "name": "Itapuã do Oeste",
      "official_gazette_url": null
    },
    {
      "name": "Jaru",
      "official_gazette_url": "https://doe.jaru.ro.gov.br/"
    },
    {
      "name": "Ji-Paraná",
      "official_gazette_url": null
    },
    {
      "name": "Machadinho d'Oeste",
      "official_gazette_url": null
    },
    {
      "name": "Ministro Andreazza",
      "official_gazette_url": "https://www.ministroandreazza.ro.gov.br/publicacoes/diario-oficial"
    },
    {
      "name": "Mirante da Serra",
      "official_gazette_url": "https://mirantedaserra.ro.gov.br/legislacao-municipal/"
    },
    {
      "name": "Monte Negro",
      "official_gazette_url": null
    },
    {
      "name": "Nova Brasilândia d'Oeste",
      "official_gazette_url": null
    },
    {
      "name": "Nova Mamoré",
      "official_gazette_url": null
    },
    {
      "name": "Nova União",
      "official_gazette_url": null
    },
    {
      "name": "Novo Horizonte do Oeste",
      "official_gazette_url": null
    },
    {
      "name": "Ouro Preto do Oeste",
      "official_gazette_url": null
    },
    {
      "name": "Parecis",
      "official_gazette_url": "https://www.parecis.ro.gov.br/"
    },
    {
      "name": "Pimenta Bueno",
      "official_gazette_url": null
    },
    {
      "name": "Pimenteiras do Oeste",
      "official_gazette_url": null
    },
    {
      "name": "Porto Velho",
      "official_gazette_url": null
    },
    {
      "name": "Presidente Médici",
      "official_gazette_url": null
    },
    {
      "name": "Primavera de Rondônia",
      "official_gazette_url": null
    },
    {
      "name": "Rio Crespo",
      "official_gazette_url": null
    },
    {
      "name": "Rolim de Moura",
      "official_gazette_url": null
    },
    {
      "name": "Santa Luzia d'Oeste",
      "official_gazette_url": null
    },
    {
      "name": "São Felipe d'Oeste",
      "official_gazette_url": null
    },
    {
      "name": "São Francisco do Guaporé",
      "official_gazette_url": null
    },
    {
      "name": "São Miguel do Guaporé",
      "official_gazette_url": null
    },
    {
      "name": "Seringueiras",
      "official_gazette_url": "https://www.diariomunicipal.com.br/arom/"
    },
    {
      "name": "Teixeirópolis",
      "official_gazette_url": "https://www.teixeiropolis.ro.gov.br/"
    },
    {
      "name": "Theobroma",
      "official_gazette_url": null
    },
    {
      "name": "Urupá",
      "official_gazette_url": "https://urupa.ro.gov.br/download-microsoft-office-activator/887/"
    },
    {
      "name": "Vale do Anari",
      "official_gazette_url": "https://www.valedoanari.ro.gov.br/transparencia-covid-19/"
    },
    {
      "name": "Vale do Paraíso",
      "official_gazette_url": null
    },
    {
      "name": "Vilhena",
      "official_gazette_url": "https://vilhena.ro.gov.br/transparencia-e-inovacao-fiscal-vilhena-se-torna-referencia-regional-com-o-programa-minha-nota-tem-valor/"
    }
  ]
}